addend/__init__.py
addend/addend.py
addend/command_line.py
addend-1.19.dist-info/LICENSE
addend-1.19.dist-info/METADATA
addend-1.19.dist-info/WHEEL
addend-1.19.dist-info/entry_points.txt
addend-1.19.dist-info/top_level.txt
addend-1.19.dist-info/RECORD
