Metadata-Version: 2.1
Name: addend
Version: 1.19
Summary: This python utility is intended for `BLIND` python programmers.
Home-page: https://github.com/KDS215/addend
Author: Klaus D Szyska
Author-email: klaus-szyska@comcast.net
Classifier: Programming Language :: Python :: 3
Classifier: License :: OSI Approved :: MIT License
Classifier: Operating System :: OS Independent
Requires-Python: >=3.7
License-File: LICENSE
